{
  "project_info": {
    "project_number": "416732496745",
    "project_id": "login-e027c",
    "storage_bucket": "login-e027c.appspot.com"
  },
  "client": [
    {
      "client_info": {
        "mobilesdk_app_id": "1:416732496745:android:9e0ff424521523df8af3f8",
        "android_client_info": {
          "package_name": "com.codingstuff.loginandsignup"
        }
      },
      "oauth_client": [
        {
          "client_id": "416732496745-hsa6iluekddnvofdd90qnlfurk7j0aun.apps.googleusercontent.com",
          "client_type": 3
        }
      ],
      "api_key": [
        {
          "current_key": "AIzaSyBsWe1oZyCOSKxcZi89j_SE_fOaM94n8hY"
        }
      ],
      "services": {
        "appinvite_service": {
          "other_platform_oauth_client": [
            {
              "client_id": "416732496745-hsa6iluekddnvofdd90qnlfurk7j0aun.apps.googleusercontent.com",
              "client_type": 3
            }
          ]
        }
      }
    },
    {
      "client_info": {
        "mobilesdk_app_id": "1:416732496745:android:57b06b430b72725e8af3f8",
        "android_client_info": {
          "package_name": "com.example.doctorapp"
        }
      },
      "oauth_client": [
        {
          "client_id": "416732496745-hsa6iluekddnvofdd90qnlfurk7j0aun.apps.googleusercontent.com",
          "client_type": 3
        }
      ],
      "api_key": [
        {
          "current_key": "AIzaSyBsWe1oZyCOSKxcZi89j_SE_fOaM94n8hY"
        }
      ],
      "services": {
        "appinvite_service": {
          "other_platform_oauth_client": [
            {
              "client_id": "416732496745-hsa6iluekddnvofdd90qnlfurk7j0aun.apps.googleusercontent.com",
              "client_type": 3
            }
          ]
        }
      }
    }
  ],
  "configuration_version": "1"
}